setup.py
distributions/Binomialdistribution.py
distributions/Gaussiandistribution.py
distributions/Generaldistribution.py
distributions/__init__.py
udacity_test_aws_course.egg-info/PKG-INFO
udacity_test_aws_course.egg-info/SOURCES.txt
udacity_test_aws_course.egg-info/dependency_links.txt
udacity_test_aws_course.egg-info/not-zip-safe
udacity_test_aws_course.egg-info/top_level.txt